timeseriestests/timeseriestests.py
TimeSeriesTests-0.1.dist-info/METADATA
TimeSeriesTests-0.1.dist-info/WHEEL
TimeSeriesTests-0.1.dist-info/top_level.txt
TimeSeriesTests-0.1.dist-info/RECORD
